pub_requests
