Metadata-Version: 1.1
Name: pub-requests
Version: 0.1.3
Summary: Utils for querying ME2_PUB
Home-page: http://git.internal.lucidmarkets.com/aashiqd/pub_requests
Author: Aashiq Dheeraj
Author-email: aashiq.dheeraj@lucidmarkets.com
License: UNKNOWN
Platform: any
Classifier: Development Status :: 2 - Pre-Alpha
Classifier: Environment :: Web Environment
Classifier: Intended Audience :: Developers
Classifier: Operating System :: OS Independent
Classifier: Programming Language :: Python
Classifier: Programming Language :: Python :: 2
Classifier: Programming Language :: Python :: 2.7
Classifier: Programming Language :: Python :: 3
Classifier: Programming Language :: Python :: 3.3
